{"body":{"coord":{"lon":-0.2617,"lat":51.522},"weather":[{"id":500,"main":"Rain","description":"light rain","icon":"10d"}],"base":"stations","main":{"temp":13.47,"feels_like":13.14,"temp_min":12.73,"temp_max":14.01,"pressure":1005,"humidity":87,"sea_level":1005,"grnd_level":1001},"visibility":10000,"wind":{"speed":7.2,"deg":240,"gust":12.35},"rain":{"1h":0.26},"clouds":{"all":75},"dt":1733412677,"sys":{"type":2,"id":2091269,"country":"GB","sunrise":1733385022,"sunset":1733414015},"timezone":0,"id":2638043,"name":"Shepherds Bush","cod":200}}