{"body":{"coord":{"lon":-0.2617,"lat":51.522},"weather":[{"id":804,"main":"Clouds","description":"overcast clouds","icon":"04n"}],"base":"stations","main":{"temp":6.96,"feels_like":2.65,"temp_min":6.34,"temp_max":7.46,"pressure":1032,"humidity":80,"sea_level":1032,"grnd_level":1028},"visibility":10000,"wind":{"speed":8.23,"deg":40},"clouds":{"all":100},"dt":1733787110,"sys":{"type":2,"id":2091269,"country":"GB","sunrise":1733730902,"sunset":1733759539},"timezone":0,"id":2638043,"name":"Shepherds Bush","cod":200}}