{"body":{"coord":{"lon":-0.2617,"lat":51.522},"weather":[{"id":803,"main":"Clouds","description":"broken clouds","icon":"04d"}],"base":"stations","main":{"temp":5.88,"feels_like":2.61,"temp_min":4.97,"temp_max":6.81,"pressure":1015,"humidity":86,"sea_level":1015,"grnd_level":1010},"visibility":10000,"wind":{"speed":4.63,"deg":340},"clouds":{"all":75},"dt":1732721391,"sys":{"type":2,"id":2091269,"country":"GB","sunrise":1732693159,"sunset":1732723118},"timezone":0,"id":2638043,"name":"Shepherds Bush","cod":200}}